dictknife/__init__.py
dictknife/__version__.py
dictknife/_sphinx.py
dictknife/accessing.py
dictknife/deepequal.py
dictknife/deepmerge.py
dictknife/guessing.py
dictknife/langhelpers.py
dictknife/mkdict.py
dictknife/naming.py
dictknife/operators.py
dictknife/pp.py
dictknife/py.typed
dictknife/shape.py
dictknife/transform.py
dictknife/walkers.py
dictknife/cliutils/__init__.py
dictknife/cliutils/extraarguments.py
dictknife/commands/__init__.py
dictknife/commands/_monkeypatch.py
dictknife/commands/dictknife.py
dictknife/commands/jsonknife.py
dictknife/commands/swaggerknife.py
dictknife/diff/__init__.py
dictknife/diff/diff.py
dictknife/diff/rows.py
dictknife/jsonknife/__init__.py
dictknife/jsonknife/_wrapped_exception.py
dictknife/jsonknife/accessor.py
dictknife/jsonknife/bundler.py
dictknife/jsonknife/example.py
dictknife/jsonknife/expander.py
dictknife/jsonknife/lifting.py
dictknife/jsonknife/merge.py
dictknife/jsonknife/patch.py
dictknife/jsonknife/relpath.py
dictknife/jsonknife/resolver.py
dictknife/jsonknife/separator.py
dictknife/loading/__init__.py
dictknife/loading/_gsuite.py
dictknife/loading/_lazyimport.py
dictknife/loading/_yaml.py
dictknife/loading/csv.py
dictknife/loading/env.py
dictknife/loading/json.py
dictknife/loading/md.py
dictknife/loading/raw.py
dictknife/loading/spreadsheet.py
dictknife/loading/toml.py
dictknife/loading/tsv.py
dictknife/loading/yaml.py
dictknife/loading/modification/__init__.py
dictknife/loading/modification/compact.py
dictknife/loading/modification/flatten.py
dictknife/loading/modification/unescape_unicode.py
dictknife/loading/modification/unescape_url.py
dictknife/swaggerknife/__init__.py
dictknife/swaggerknife/flatten.py
dictknife/swaggerknife/json2swagger.py
dictknife/swaggerknife/migration.py
dictknife/tests/__init__.py
dictknife/tests/test_accessing_accessor.py
dictknife/tests/test_accessing_scope.py
dictknife/tests/test_deepequal.py
dictknife/tests/test_deepmerge.py
dictknife/tests/test_diff.py
dictknife/tests/test_guessing.py
dictknife-0.14.2.dist-info/METADATA
dictknife-0.14.2.dist-info/WHEEL
dictknife-0.14.2.dist-info/entry_points.txt
dictknife-0.14.2.dist-info/licenses/LICENSE
dictknife-0.14.2.dist-info/RECORD
